workpy/__init__.py
workpy/base.py
workpy-0.0.1.dist-info/LICENSE
workpy-0.0.1.dist-info/METADATA
workpy-0.0.1.dist-info/WHEEL
workpy-0.0.1.dist-info/top_level.txt
workpy-0.0.1.dist-info/RECORD
