Metadata-Version: 2.1
Name: workpy
Version: 0.0.1
Summary: working with python
Home-page: https://github.com/cofear/workpy
Author: cofear
Author-email: cofear@163.com
License: UNKNOWN
Platform: UNKNOWN
Classifier: Programming Language :: Python :: 3
Classifier: License :: OSI Approved :: MIT License
Classifier: Operating System :: OS Independent
